mystace/__init__.py
mystace/_version.py
mystace/exceptions.py
mystace/mustache_tree.py
mystace/py.typed
mystace/tokenize.py
mystace/util.py
mystace-1.0.1.dist-info/METADATA
mystace-1.0.1.dist-info/WHEEL
mystace-1.0.1.dist-info/licenses/LICENSE
mystace-1.0.1.dist-info/RECORD
