Metadata-Version: 2.4
Name: mystace
Version: 1.0.1
Summary: Rendering mustache templates in Python fast.
Author-email: Eliot Robson <eliot.robson24@gmail.com>
License: MIT
License-File: LICENSE
Classifier: Development Status :: 4 - Beta
Classifier: License :: OSI Approved :: MIT License
Classifier: Programming Language :: Python :: 3.10
Classifier: Programming Language :: Python :: 3.11
Classifier: Programming Language :: Python :: 3.12
Classifier: Programming Language :: Python :: 3.13
Classifier: Programming Language :: Python :: 3.14
Classifier: Topic :: Text Processing :: Markup
Requires-Python: >=3.10
Requires-Dist: more-itertools>=8
Requires-Dist: typing-extensions>=4.15.0
